stashconnect/__init__.py
stashconnect/account.py
stashconnect/authentication.py
stashconnect/channels.py
stashconnect/client.py
stashconnect/companies.py
stashconnect/conversations.py
stashconnect/crypto_utils.py
stashconnect/files.py
stashconnect/messages.py
stashconnect/models.py
stashconnect/tools.py
stashconnect/users.py
stashconnect-0.9.65.dist-info/LICENSE
stashconnect-0.9.65.dist-info/METADATA
stashconnect-0.9.65.dist-info/WHEEL
stashconnect-0.9.65.dist-info/top_level.txt
stashconnect-0.9.65.dist-info/RECORD
