Metadata-Version: 2.1
Name: stashconnect
Version: 0.9.65
Summary: An API wrapper for stashcat and schul.cloud.
Home-page: https://github.com/BuStudios/StashConnect
Author: BuStudios
Author-email: support@bustudios.org
Project-URL: Bug Tracker, https://github.com/BuStudios/StashConnect/issues
Project-URL: Documentation, https://github.com/BuStudios/StashConnect/wiki
Project-URL: Source Code, https://github.com/BuStudios/StashConnect
Keywords: stashconnect,stashcat api,stashcat python,schul.cloud api,schul.cloud python,stashcat bot,schul.cloud bot
Classifier: Programming Language :: Python :: 3
Classifier: License :: OSI Approved :: MIT License
Classifier: Operating System :: OS Independent
Classifier: Intended Audience :: Developers
Classifier: Development Status :: 4 - Beta
Requires-Python: >=3.10
License-File: LICENSE
Requires-Dist: requests
Requires-Dist: pycryptodome
Requires-Dist: python-socketio
Requires-Dist: Pillow
Requires-Dist: websocket-client
